openpyxl_templates/__init__.py
openpyxl_templates/demo.py
openpyxl_templates/exceptions.py
openpyxl_templates/styles.py
openpyxl_templates/templated_sheet.py
openpyxl_templates/templated_workbook.py
openpyxl_templates/utils.py
openpyxl_templates/table_sheet/__init__.py
openpyxl_templates/table_sheet/columns.py
openpyxl_templates/table_sheet/table_sheet.py
tests/test_table_sheet/__init__.py
tests/test_table_sheet/test_table_column.py
tests/test_table_sheet/test_table_sheet.py
openpyxl_templates-0.2.4.dist-info/LICENSE
openpyxl_templates-0.2.4.dist-info/METADATA
openpyxl_templates-0.2.4.dist-info/WHEEL
openpyxl_templates-0.2.4.dist-info/top_level.txt
openpyxl_templates-0.2.4.dist-info/RECORD
