Metadata-Version: 2.1
Name: openpyxl-templates
Version: 0.2.4
Summary: Openpyxl-templates is an extention to openpyxl which simplifies reading and writing excelfiles by formalizing their structure into templates.
Home-page: https://github.com/SverkerSbrg/openpyxl-templates
Author: Sverker Sjöberg
Author-email: UNKNOWN
License: MIT
Platform: UNKNOWN
Classifier: Development Status :: 3 - Alpha
Classifier: Intended Audience :: Developers
Classifier: License :: OSI Approved :: MIT License
Classifier: Operating System :: OS Independent
Classifier: Programming Language :: Python
Classifier: Programming Language :: Python :: 3
Classifier: Programming Language :: Python :: 3.4
Classifier: Programming Language :: Python :: 3.5
Classifier: Programming Language :: Python :: 3.6
Classifier: Programming Language :: Python :: Implementation :: PyPy
Requires-Dist: openpyxl
Requires-Dist: fortnum
